tests/__init__.py
tests/test_html.py
tests/test_mrss.py
tests/test_odysee.py
tests/test_peertube.py
tests/test_rumble.py
tests/test_timcast.py
tests/test_twitter.py
videosrc/__init__.py
videosrc/__main__.py
videosrc/errors.py
videosrc/utils.py
videosrc/crawlers/__init__.py
videosrc/crawlers/base.py
videosrc/crawlers/html.py
videosrc/crawlers/mrss.py
videosrc/crawlers/odysee.py
videosrc/crawlers/peertube.py
videosrc/crawlers/rumble.py
videosrc/crawlers/timcast.py
videosrc/crawlers/twitter.py
videosrc/crawlers/youtube.py
videosrc/models/__init__.py
videosrc-0.1.10.dist-info/LICENSE
videosrc-0.1.10.dist-info/METADATA
videosrc-0.1.10.dist-info/WHEEL
videosrc-0.1.10.dist-info/top_level.txt
videosrc-0.1.10.dist-info/RECORD
