Metadata-Version: 2.1
Name: videosrc
Version: 0.1.10
Summary: Video src crawler
Home-page: https://github.com/cesium-tv/videosrc/
Author: Ben Timby
Author-email: btimby@gmail.com
License-File: LICENSE
Requires-Dist: aiohttp-scraper (==0.1.4)
Requires-Dist: pyppeteer (==1.0.2)
Requires-Dist: beautifulsoup4 (==4.10.0)
Requires-Dist: requests (==2.25.1)
Requires-Dist: av (==9.2.0)
Requires-Dist: snscrape (==0.6.2.20230320)
Requires-Dist: Pillow (==9.5.0)
Requires-Dist: pytube (==15.0.0)
Provides-Extra: dev
Requires-Dist: flake8 ; extra == 'dev'
Requires-Dist: responses-server ; extra == 'dev'
